translate/__init__.py
translate/__main__.py
translate/constants.py
translate/exceptions.py
translate/main.py
translate/translate.py
translate/version.py
translate/providers/__init__.py
translate/providers/baidu.py
translate/providers/base.py
translate/providers/bing.py
translate/providers/deepl.py
translate/providers/google.py
translate/providers/mymemory.py
translate/providers/tencent.py
translate/providers/youdao.py
multi_translate-1.0.0.dist-info/LICENSE
multi_translate-1.0.0.dist-info/METADATA
multi_translate-1.0.0.dist-info/WHEEL
multi_translate-1.0.0.dist-info/entry_points.txt
multi_translate-1.0.0.dist-info/top_level.txt
multi_translate-1.0.0.dist-info/RECORD
