Metadata-Version: 2.1
Name: multi-translate
Version: 1.0.0
Summary: Concurrently request multiple translation platforms. Support Baidu, Bing, Deepl, Google, MyMemory, Tencent, Youdao.
Home-page: https://github.com/Lyndon1994/multi-translate
Author: Robin Lin
Author-email: wuhulinyi@gmail.com
License: MIT
Keywords: translate translation command line multi youdao tencent baidu
Platform: UNKNOWN
Classifier: Development Status :: 5 - Production/Stable
Classifier: Intended Audience :: Education
Classifier: Intended Audience :: End Users/Desktop
Classifier: Intended Audience :: Developers
Classifier: License :: OSI Approved :: MIT License
Classifier: Operating System :: OS Independent
Classifier: Programming Language :: Python :: 3.6
Classifier: Programming Language :: Python
Classifier: Topic :: Education
License-File: LICENSE
Requires-Dist: click
Requires-Dist: lxml
Requires-Dist: requests
Requires-Dist: requests-async
